odoo8_addon_website_breadcrumb-8.0.1.0.0.99.dev10-py3.8-nspkg.pth
odoo_addons/website_breadcrumb/README.rst
odoo_addons/website_breadcrumb/__init__.py
odoo_addons/website_breadcrumb/__openerp__.py
odoo_addons/website_breadcrumb/i18n/ca.po
odoo_addons/website_breadcrumb/i18n/de.po
odoo_addons/website_breadcrumb/i18n/el_GR.po
odoo_addons/website_breadcrumb/i18n/es.po
odoo_addons/website_breadcrumb/i18n/fr.po
odoo_addons/website_breadcrumb/i18n/it.po
odoo_addons/website_breadcrumb/i18n/pt_BR.po
odoo_addons/website_breadcrumb/i18n/ru.po
odoo_addons/website_breadcrumb/i18n/sl.po
odoo_addons/website_breadcrumb/i18n/website_breadcrumb.pot
odoo_addons/website_breadcrumb/models/__init__.py
odoo_addons/website_breadcrumb/models/website.py
odoo_addons/website_breadcrumb/static/description/icon.png
odoo_addons/website_breadcrumb/static/description/icon.svg
odoo_addons/website_breadcrumb/views/layout.xml
odoo_addons/website_breadcrumb/views/templates.xml
odoo8_addon_website_breadcrumb-8.0.1.0.0.99.dev10.dist-info/METADATA
odoo8_addon_website_breadcrumb-8.0.1.0.0.99.dev10.dist-info/WHEEL
odoo8_addon_website_breadcrumb-8.0.1.0.0.99.dev10.dist-info/namespace_packages.txt
odoo8_addon_website_breadcrumb-8.0.1.0.0.99.dev10.dist-info/top_level.txt
odoo8_addon_website_breadcrumb-8.0.1.0.0.99.dev10.dist-info/RECORD
